fline-0.1.3.dist-info/licenses/LICENSE
flowline/__init__.py
flowline/config.py
flowline/api/__init__.py
flowline/api/interface.py
flowline/api/routes.py
flowline/api/routes_test.py
flowline/core/__init__.py
flowline/core/gpu.py
flowline/core/process.py
flowline/core/program.py
flowline/core/task.py
flowline/utils/__init__.py
flowline/utils/log.py
fline-0.1.3.dist-info/METADATA
fline-0.1.3.dist-info/WHEEL
fline-0.1.3.dist-info/top_level.txt
fline-0.1.3.dist-info/RECORD
