Metadata-Version: 2.4
Name: fline
Version: 0.1.3
Summary: Automated tool for running Python programs in a streamlined manner
Home-page: https://github.com/Dramwig/FlowLine
Author: Dramwig
Author-email: dramwig@gmail.com
License: Apache Software License
Keywords: flowline,fline,machine-learning,automation,flash,gpu,gpu-monitoring,experiment-management
Classifier: Programming Language :: Python :: 3
Classifier: License :: OSI Approved :: Apache Software License
Classifier: Operating System :: OS Independent
Requires-Python: >=3.6
License-File: LICENSE
Requires-Dist: Flask==2.0.1
Requires-Dist: Flask_Cors==3.0.10
Requires-Dist: Flask_SocketIO==5.5.1
Requires-Dist: nvidia_ml_py==12.560.30
Requires-Dist: pandas==2.3.1
Requires-Dist: psutil==5.9.0
Requires-Dist: pynvml==11.0.0
Requires-Dist: tqdm==4.66.5
Requires-Dist: werkzeug==2.3
Requires-Dist: openpyxl
Dynamic: author
Dynamic: author-email
Dynamic: classifier
Dynamic: description
Dynamic: description-content-type
Dynamic: home-page
Dynamic: keywords
Dynamic: license
Dynamic: license-file
Dynamic: requires-dist
Dynamic: requires-python
Dynamic: summary
